icodeai_dev_db/__init__.py
icodeai_dev_db/callback/__init__.py
icodeai_dev_db/callback/call_back.py
icodeai_dev_db/extractors/__init__.py
icodeai_dev_db/extractors/base_extractor.py
icodeai_dev_db/extractors/base_postgres_metadata.py
icodeai_dev_db/extractors/csv_extractor.py
icodeai_dev_db/extractors/generic_extractor.py
icodeai_dev_db/extractors/neo4j_es_last_updated_extractor.py
icodeai_dev_db/extractors/neo4j_extractor.py
icodeai_dev_db/extractors/neo4j_search_data_extractor.py
icodeai_dev_db/extractors/postgres_metadata.py
icodeai_dev_db/extractors/sqlalchemy_extractor.py
icodeai_dev_db/job/__init__.py
icodeai_dev_db/job/base_job.py
icodeai_dev_db/job/job.py
icodeai_dev_db/loader/__init__.py
icodeai_dev_db/loader/base_loader.py
icodeai_dev_db/loader/file_system_elasticsearch_json_loader.py
icodeai_dev_db/loader/file_system_neo4j_csv_loader.py
icodeai_dev_db/models/__init__.py
icodeai_dev_db/models/badge.py
icodeai_dev_db/models/cluster/__init__.py
icodeai_dev_db/models/cluster/constants.py
icodeai_dev_db/models/documents/__init__.py
icodeai_dev_db/models/documents/elastic_search.py
icodeai_dev_db/models/graphs/__init__.py
icodeai_dev_db/models/graphs/node.py
icodeai_dev_db/models/graphs/relationship.py
icodeai_dev_db/models/graphs/serializable.py
icodeai_dev_db/models/schema/__init__.py
icodeai_dev_db/models/schema/constants.py
icodeai_dev_db/models/schema/schema.py
icodeai_dev_db/models/table/__init__.py
icodeai_dev_db/models/table/es_document.py
icodeai_dev_db/models/table/metadata.py
icodeai_dev_db/publisher/__init__.py
icodeai_dev_db/publisher/base_publisher.py
icodeai_dev_db/publisher/elasticsearch_constants.py
icodeai_dev_db/publisher/elasticsearch_publisher.py
icodeai_dev_db/publisher/neo4j_csv_publisher.py
icodeai_dev_db/publisher/neo4j_preprocessor.py
icodeai_dev_db/serializers/__init__.py
icodeai_dev_db/serializers/neo4j.py
icodeai_dev_db/task/__init__.py
icodeai_dev_db/task/base_task.py
icodeai_dev_db/task/task.py
icodeaidev_databuilder-0.0.3.dist-info/METADATA
icodeaidev_databuilder-0.0.3.dist-info/WHEEL
icodeaidev_databuilder-0.0.3.dist-info/top_level.txt
icodeaidev_databuilder-0.0.3.dist-info/RECORD
