Metadata-Version: 2.1
Name: icodeaidev-databuilder
Version: 0.0.3
Summary: IcodeAI Data builder
Home-page: UNKNOWN
Maintainer: Chepkoy Allan
Maintainer-email: allankiplangat22@gmail.com
License: UNKNOWN
Platform: UNKNOWN
Classifier: Programming Language :: Python :: 3.6
Classifier: Programming Language :: Python :: 3.7
Requires-Python: >=3.6
Requires-Dist: pyhocon (>=0.3.42)
Requires-Dist: neo4j-driver (<4.0,>=1.7.2)
Requires-Dist: pytz (>=2018.4)
Requires-Dist: statsd (>=3.2.1)
Requires-Dist: retrying (>=1.3.3)
Requires-Dist: requests (<3.0,>=2.23.0)
Requires-Dist: elasticsearch (<7.0,>=6.2.0)
Requires-Dist: unidecode
Requires-Dist: Jinja2 (<2.12,>=2.10.0)
Requires-Dist: pandas (<1.2.0,>=0.21.0)
